gpt4pandas/__init__.py
gpt4pandas-0.2.dist-info/LICENSE
gpt4pandas-0.2.dist-info/METADATA
gpt4pandas-0.2.dist-info/WHEEL
gpt4pandas-0.2.dist-info/top_level.txt
gpt4pandas-0.2.dist-info/RECORD
