Metadata-Version: 2.1
Name: gpt4pandas
Version: 0.2
Summary: A tool that uses the GPT4ALL language model and the Pandas library to answer questions about dataframes
Author: ParisNeo (Saifeddine ALOUI)
Author-email: aloui.seifeddine@gmail.com
License: Apache License 2.0
Keywords: pandas GPT4ALL QA
License-File: LICENSE
Requires-Dist: pandas
Requires-Dist: transformers
Requires-Dist: pyllamacpp (==2.1.1)
